[
    {
        "platform": "linkedin",
        "url": "https://in.linkedin.com/company/weprspr",
        "icon": "linkedin.svg"
    },

    {
        "platform": "mastodon",
        "url": "https://mastodon.social/@WePRSPR",
        "icon": "mastodon.svg"
    },

    {
        "platform": "twitter",
        "url": "https://twitter.com/WePRSPR",
        "icon": "twitter.svg"
    },
        {
        "platform": "facebook",
        "url": "https://www.facebook.com/WePrspr-118673681197154",
        "icon": "facebook.svg"
    },
    {
        "platform": "instagram",
        "url": "https://www.instagram.com/WePRSPR/",
        "icon": "instagram.svg"
    },
    {
        "platform": "rss",
        "url": "/feed.xml",
        "icon": "rss.svg"
    }
]
